{"data": [{"keyword": "파라다이스그레인", "avg_recent_3": 7454, "avg_prev_7": 3469, "velocity_score": 114.9}, {"keyword": "활새우", "avg_recent_3": 1231, "avg_prev_7": 728, "velocity_score": 69.1}, {"keyword": "마그네슘", "avg_recent_3": 4360, "avg_prev_7": 3025, "velocity_score": 44.1}, {"keyword": "생새우", "avg_recent_3": 2648, "avg_prev_7": 1899, "velocity_score": 39.5}, {"keyword": "임박", "avg_recent_3": 353, "avg_prev_7": 259, "velocity_score": 35.9}, {"keyword": "구운계란", "avg_recent_3": 2221, "avg_prev_7": 1680, "velocity_score": 32.2}, {"keyword": "갑오징어", "avg_recent_3": 2054, "avg_prev_7": 1563, "velocity_score": 31.4}, {"keyword": "토마토즙", "avg_recent_3": 335, "avg_prev_7": 256, "velocity_score": 30.8}, {"keyword": "야채도사", "avg_recent_3": 3954, "avg_prev_7": 3032, "velocity_score": 30.4}, {"keyword": "애사비", "avg_recent_3": 2877, "avg_prev_7": 2257, "velocity_score": 27.5}], "updated_at": "2026-06-25 09:54:20"}